[
  {
    "imageUrl": "https://images.pexels.com/photos/280229/pexels-photo-280229.jpeg?auto=compress&cs=tinysrgb&w=1260&h=750&dpr=1",
    "title": "Golden Horizon Manor",
    "description": "A cozy cabin in the woods with a fireplace, a hot tub, and a stunning view of the lake.",
    "rooms": 3
  },
  {
    "imageUrl": "https://images.pexels.com/photos/259588/pexels-photo-259588.jpeg?auto=compress&cs=tinysrgb&w=1260&h=750&dpr=1",
    "title": "Starry Nights Chalet",
    "description": "A spacious house in the suburbs with a pool, a game room, and a home theater.",
    "rooms": 2
  },
  {
    "imageUrl": "https://images.pexels.com/photos/1029599/pexels-photo-1029599.jpeg?auto=compress&cs=tinysrgb&w=1260&h=750&dpr=1",
    "title": "Enchanted Oak Manor",
    "description": "A charming cottage in the countryside with a garden, a library, and a wood-burning stove.",
    "rooms": 1
  },
  {
    "imageUrl": "https://images.pexels.com/photos/106399/pexels-photo-106399.jpeg?auto=compress&cs=tinysrgb&w=1260&h=750&dpr=1",
    "title": "Victorian Rose Residence",
    "description": "A modern apartment in the city with a balcony, a gym, and a rooftop lounge.",
    "rooms": 1
  },
  {
    "imageUrl": "https://images.pexels.com/photos/53610/large-home-residential-house-architecture-53610.jpeg?auto=compress&cs=tinysrgb&w=1260&h=750&dpr=1",
    "title": "Lakeside Tranquility",
    "description": "A rustic farmhouse in the vineyard with a kitchen, a wine cellar, and a patio.",
    "rooms": 1
  },
  {
    "imageUrl": "https://images.pexels.com/photos/1396132/pexels-photo-1396132.jpeg?auto=compress&cs=tinysrgb&w=1260&h=750&dpr=1",
    "title": "Seaside Solace Cottage",
    "description": "A beachfront villa in the tropics with a hammock, a jet ski, and a private beach.",
    "rooms": 2
  },
  {
    "imageUrl": "https://images.pexels.com/photos/208736/pexels-photo-208736.jpeg?auto=compress&cs=tinysrgb&w=1260&h=750&dpr=1",
    "title": "Willowbrook Retreat",
    "description": "A luxury penthouse in the skyscraper with a jacuzzi, a sauna, and a helipad.",
    "rooms": 2
  },
  {
    "imageUrl": "https://images.pexels.com/photos/221024/pexels-photo-221024.jpeg?auto=compress&cs=tinysrgb&w=1260&h=750&dpr=1",
    "title": "Garden Gate Oasis",
    "description": "A historic mansion in the hills with a ballroom, a museum, and a secret passage.",
    "rooms": 3
  },
  {
    "imageUrl": "https://images.pexels.com/photos/1612351/pexels-photo-1612351.jpeg?auto=compress&cs=tinysrgb&w=1260&h=750&dpr=1",
    "title": "Country Side",
    "description": "A tiny house on wheels with a loft, a solar panel, and a composting toilet.",
    "rooms": 1
  },
  {
    "imageUrl": "https://images.pexels.com/photos/262405/pexels-photo-262405.jpeg?auto=compress&cs=tinysrgb&w=1260&h=750&dpr=1",
    "title": "Moonlit Meadows Estate",
    "description": "A log cabin in the mountains with a ski lift, a fireplace, and a snowman.",
    "rooms": 2
  },
  {
    "imageUrl": "https://images.pexels.com/photos/2091166/pexels-photo-2091166.jpeg?auto=compress&cs=tinysrgb&w=1260&h=750&dpr=1",
    "title": "Tranquil Waterside Villa",
    "description": "A colonial house in the town with a porch, a garage, and a swing set.",
    "rooms": 1
  },
  {
    "imageUrl": "https://images.pexels.com/photos/463734/pexels-photo-463734.jpeg?auto=compress&cs=tinysrgb&w=1260&h=750&dpr=1",
    "title": "Azure Skies Bungalow",
    "description": "A treehouse in the jungle with a zip line, a monkey, and a treasure map.",
    "rooms": 2
  },
  {
    "imageUrl": "https://images.unsplash.com/photo-1510004868592-324954d4d45a?w=500&auto=format&fit=crop&q=60&ixlib=rb-4.0.3&ixid=M3wxMjA3fDB8MHxzZWFyY2h8MTU5fHxob3VzZXN8ZW58MHx8MHx8fDI%3D",
    "title": "Rustic Charm Hideaway",
    "description": "A studio apartment in the arts district with a mural, a piano, and a coffee shop.",
    "rooms": 2
  },
  {
    "imageUrl": "https://images.pexels.com/photos/259685/pexels-photo-259685.jpeg?auto=compress&cs=tinysrgb&w=1260&h=750&dpr=1",
    "title": "Whispering Pines Retreat",
    "description": "A houseboat on the river with a fishing rod, a kayak, and a dolphin.",
    "rooms": 4
  },
  {
    "imageUrl": "https://images.pexels.com/photos/2155202/pexels-photo-2155202.jpeg?auto=compress&cs=tinysrgb&w=1260&h=750&dpr=1",
    "title": "Breeze Heaven",
    "description": "A yurt in the desert with a tent, a camel, and a starry sky.",
    "rooms": 2
  },
  {
    "imageUrl": "https://images.pexels.com/photos/460695/pexels-photo-460695.jpeg?auto=compress&cs=tinysrgb&w=1260&h=750&dpr=1",
    "title": "Whimsical Woodland Lodge",
    "description": "A castle in the clouds with a dragon, a wizard, and a magic wand.",
    "rooms": 2
  },
  {
    "imageUrl": "https://images.pexels.com/photos/1268871/pexels-photo-1268871.jpeg?auto=compress&cs=tinysrgb&w=1260&h=750&dpr=1",
    "title": "Sunset Serenity Cottage",
    "description": "A bungalow in the island with a hut, a coconut, and a volcano.",
    "rooms": 4
  },
  {
    "imageUrl": "https://images.pexels.com/photos/2326926/pexels-photo-2326926.jpeg?auto=compress&cs=tinysrgb&w=1260&h=750&dpr=1",
    "title": "Maplewood Manor",
    "description": "A dome in the mars with a greenhouse, a rover, and a telescope.",
    "rooms": 3
  },
  {
    "imageUrl": "https://images.pexels.com/photos/1438834/pexels-photo-1438834.jpeg?auto=compress&cs=tinysrgb&w=1260&h=750&dpr=1",
    "title": "Harborview Haven",
    "description": "A igloo in the arctic with a sled, a penguin, and a polar bear.",
    "rooms": 4
  },
  {
    "imageUrl": "https://images.pexels.com/photos/1127119/pexels-photo-1127119.jpeg?auto=compress&cs=tinysrgb&w=1260&h=750&dpr=1",
    "title": "Mountain Mist Lodge",
    "description": "A hobbit hole in the shire with a pipe, a ring, and a wizard.",
    "rooms": 3
  }
]